LICENSE
README.md
setup.py
rq_chains/__init__.py
rq_chains/chains_job.py
rq_chains/decorators.py
rq_chains/exceptions.py
rq_chains/redis_ops.py
rq_chains/walk.py
rq_chains.egg-info/PKG-INFO
rq_chains.egg-info/SOURCES.txt
rq_chains.egg-info/dependency_links.txt
rq_chains.egg-info/requires.txt
rq_chains.egg-info/top_level.txt