Metadata-Version: 2.1
Name: rq-chains
Version: 0.1.5
Summary: RQ Chains is a Python library that extends RQ (Redis Queue) with a publisher-subscriber model for job chains. By Khalid Grandi (github.com/xaled).
Home-page: https://github.com/xaled/rq-chains
Author: Khalid Grandi
Author-email: kh.grandi@gmail.com
License: MIT
Keywords: library rq redis pubsub
Platform: UNKNOWN
Classifier: License :: OSI Approved :: MIT License
Classifier: Operating System :: OS Independent
Classifier: Programming Language :: Python
Requires-Python: >=3
License-File: LICENSE
